python_aternos/__init__.py
python_aternos/ataccount.py
python_aternos/atclient.py
python_aternos/atconf.py
python_aternos/atconnect.py
python_aternos/aterrors.py
python_aternos/atfile.py
python_aternos/atfm.py
python_aternos/atjsparse.py
python_aternos/atlog.py
python_aternos/atmd5.py
python_aternos/atplayers.py
python_aternos/atserver.py
python_aternos/atwss.py
python_aternos-3.0.6.dist-info/LICENSE
python_aternos-3.0.6.dist-info/METADATA
python_aternos-3.0.6.dist-info/NOTICE
python_aternos-3.0.6.dist-info/WHEEL
python_aternos-3.0.6.dist-info/top_level.txt
python_aternos-3.0.6.dist-info/RECORD
