Metadata-Version: 2.1
Name: python-aternos
Version: 3.0.6
Summary: An unofficial Aternos API
Home-page: https://github.com/DarkCat09/python-aternos
Author: Andrey @DarkCat09
Author-email: py@dc09.ru
Project-URL: Documentation, https://python-aternos.codeberg.page
Project-URL: GitHub, https://github.com/DarkCat09/python-aternos
Project-URL: Bug Tracker, https://github.com/DarkCat09/python-aternos/issues
Classifier: Development Status :: 4 - Beta
Classifier: Programming Language :: Python :: 3
Classifier: Programming Language :: Python :: 3.7
Classifier: Programming Language :: Python :: 3.8
Classifier: Programming Language :: Python :: 3.9
Classifier: Programming Language :: Python :: 3.10
Classifier: Programming Language :: Python :: 3.11
Classifier: License :: OSI Approved :: Apache Software License
Classifier: Operating System :: OS Independent
Classifier: Operating System :: Microsoft :: Windows
Classifier: Operating System :: POSIX :: Linux
Classifier: Operating System :: MacOS
Classifier: Intended Audience :: Developers
Classifier: Topic :: Internet
Classifier: Typing :: Typed
Requires-Python: >=3.7
License-File: LICENSE
License-File: NOTICE
Requires-Dist: cloudscraper==1.2.71
Requires-Dist: Js2Py==0.74
Requires-Dist: lxml==4.9.2
Requires-Dist: regex==2023.6.3
Requires-Dist: websockets==11.0.3
Provides-Extra: dev
Requires-Dist: autopep8==2.0.2; extra == "dev"
Requires-Dist: pycodestyle==2.10.0; extra == "dev"
Requires-Dist: mypy==1.4.1; extra == "dev"
Requires-Dist: pylint==2.17.4; extra == "dev"
Requires-Dist: requests-mock==1.11.0; extra == "dev"
Requires-Dist: types-requests==2.31.0.1; extra == "dev"
Provides-Extra: pypi
Requires-Dist: build==0.10.0; extra == "pypi"
Requires-Dist: twine==4.0.2; extra == "pypi"
Provides-Extra: docs
Requires-Dist: mkdocs==1.4.3; extra == "docs"
Requires-Dist: mkdocstrings[python]==0.22.0; extra == "docs"
